ai_helper_utils/__init__.py
ai_helper_utils/core.py
ai_helper_utils-0.5.0.dist-info/METADATA
ai_helper_utils-0.5.0.dist-info/WHEEL
ai_helper_utils-0.5.0.dist-info/top_level.txt
ai_helper_utils-0.5.0.dist-info/RECORD
