Metadata-Version: 2.4
Name: ai_helper_utils
Version: 0.5.0
Summary: A helper library for AI tasks
Author: Antigravity
Classifier: Programming Language :: Python :: 3
Classifier: License :: OSI Approved :: MIT License
Classifier: Operating System :: OS Independent
Requires-Python: >=3.6
Requires-Dist: requests
Requires-Dist: google-generativeai
Dynamic: author
Dynamic: classifier
Dynamic: requires-dist
Dynamic: requires-python
Dynamic: summary
